ks_realpython_reader-1.0.0.dist-info/METADATA
ks_realpython_reader-1.0.0.dist-info/RECORD
ks_realpython_reader-1.0.0.dist-info/WHEEL
ks_realpython_reader-1.0.0.dist-info/entry_points.txt
ks_realpython_reader-1.0.0.dist-info/top_level.txt
reader/__init__.py
reader/__main__.py
reader/config.cfg
reader/feed.py
reader/viewer.py
