Metadata-Version: 2.1
Name: ks-realpython-reader
Version: 1.0.0
Summary: Read the latest Real Python tutorials
Home-page: https://github.com/Kashyap12/reade
Author: Cloned from Real Python
Author-email: sharmakashyap12@gmail.com
License: MIT
Platform: UNKNOWN
Classifier: License :: OSI Approved :: MIT License
Classifier: Programming Language :: Python
Classifier: Programming Language :: Python :: 2
Classifier: Programming Language :: Python :: 3
Requires-Dist: feedparser
Requires-Dist: html2text
Requires-Dist: importlib-resources
Requires-Dist: typing
